sav/channels/__init__.py
sav/channels/py.typed
sav.channels-0.5.dist-info/LICENSE
sav.channels-0.5.dist-info/METADATA
sav.channels-0.5.dist-info/WHEEL
sav.channels-0.5.dist-info/top_level.txt
sav.channels-0.5.dist-info/RECORD
