Metadata-Version: 2.1
Name: sav.channels
Version: 0.5
Summary: Channels between coroutines
Home-page: https://github.com/sandervoerman/channels
Author: Sander Voerman
Author-email: sander@savoerman.nl
License: UNKNOWN
Platform: UNKNOWN
Classifier: Development Status :: 4 - Beta
Classifier: Programming Language :: Python :: 3.8
Classifier: License :: OSI Approved :: MIT License
Classifier: Operating System :: OS Independent
Requires-Python: >=3.8
